AreaNumber.py
ChinaID.py
Verification.py
setup.py
ChinaID.egg-info/PKG-INFO
ChinaID.egg-info/SOURCES.txt
ChinaID.egg-info/dependency_links.txt
ChinaID.egg-info/requires.txt
ChinaID.egg-info/top_level.txt