Metadata-Version: 1.0
Name: ChinaID
Version: 0.0.0
Summary: Verify the Chinese identity card number and obtain the information from it
Home-page: https://github.com/Pandorym/ChinaID
Author: Pandorym
Author-email: Pandorym@foxmail.com
License: AGPL-3.0
Platform: any
